README.rst
setup.cfg
setup.py
fodder/__init__.py
fodder/features.py
fodder.egg-info/PKG-INFO
fodder.egg-info/SOURCES.txt
fodder.egg-info/dependency_links.txt
fodder.egg-info/entry_points.txt
fodder.egg-info/not-zip-safe
fodder.egg-info/requires.txt
fodder.egg-info/top_level.txt
fodder/scripts/__init__.py
fodder/scripts/cli.py