Metadata-Version: 1.0
Name: fodder
Version: 1.0.0.dev0
Summary: Feature oriented development
Home-page: https://github.com/dreki/py-fodder
Author: Sean Gilbertson
Author-email: sean.gilbertson@gmail.com
License: MIT
Platform: UNKNOWN
